face_test_cpu/__init__.py
face_test_cpu/bbox_anchor.py
face_test_cpu/get_config.py
face_test_cpu/print_info.py
face_test_cpu/data/__init__.py
face_test_cpu/data/constant.py
face_test_cpu/data/image.py
face_test_cpu/data/experiments/__init__.py
face_test_cpu/data/experiments/AFLW/__init__.py
face_test_cpu/data/experiments/AFLW/pip_32_16_60_r18_l2_l1_10_1_nb10.py
face_test_cpu/data/experiments/COFW/__init__.py
face_test_cpu/data/experiments/COFW/pip_32_16_60_r18_l2_l1_10_1_nb10.py
face_test_cpu/data/experiments/WFLW/__init__.py
face_test_cpu/data/experiments/WFLW/pip_32_16_60_mv3_large_l2_l1_10_1_nb10.py
face_test_cpu/data/experiments/WFLW/pip_32_16_60_mv3_small_l2_l1_10_1_nb10.py
face_test_cpu/data/experiments/WFLW/pip_32_16_60_r18_l2_l1_10_1_nb10.py
face_test_cpu/data/experiments/data_300W/__init__.py
face_test_cpu/data/experiments/data_300W/pip_32_16_60_r18_l2_l1_10_1_nb10.py
face_test_cpu/face/__init__.py
face_test_cpu/face/common.py
face_test_cpu/face/get_result.py
face_test_cpu/model_zoo/__init__.py
face_test_cpu/model_zoo/get_models.py
face_test_cpu/model_zoo/model_attribute/__init__.py
face_test_cpu/model_zoo/model_attribute/arcface_GenderAge.py
face_test_cpu/model_zoo/model_attribute/arcface_Race.py
face_test_cpu/model_zoo/model_common/__init__.py
face_test_cpu/model_zoo/model_common/load_onnx.py
face_test_cpu/model_zoo/model_common/load_openvino.py
face_test_cpu/model_zoo/model_detection/__init__.py
face_test_cpu/model_zoo/model_detection/blazeface.py
face_test_cpu/model_zoo/model_detection/blazeface640.py
face_test_cpu/model_zoo/model_detection/retinaface_insightface.py
face_test_cpu/model_zoo/model_detection/retinaface_torch.py
face_test_cpu/model_zoo/model_detection/scrfd.py
face_test_cpu/model_zoo/model_landmark/__init__.py
face_test_cpu/model_zoo/model_landmark/det2d106.py
face_test_cpu/model_zoo/model_landmark/pipnet.py
face_test_cpu/model_zoo/model_landmark/tddfa.py
face_test_cpu/model_zoo/model_recognition/__init__.py
face_package_cpu-1.1.26.dist-info/METADATA
face_package_cpu-1.1.26.dist-info/WHEEL
face_package_cpu-1.1.26.dist-info/top_level.txt
face_package_cpu-1.1.26.dist-info/RECORD
