Metadata-Version: 2.1
Name: face-package-cpu
Version: 1.1.26
Summary: Test Face model _ CPU
Author: minsuny
Author-email: minsun.y@nsensecorp.com
Requires-Python: >=3
Requires-Dist: onnxruntime
Requires-Dist: openvino (==2022.2.0)
Requires-Dist: scikit-image
Requires-Dist: scikit-learn
Requires-Dist: pillow
Requires-Dist: opencv-python
